tor/__init__.py
tor/drama.py
tor/main.py
tor/rules.py
tor/story.py
tor/types.py
tor/dialogue/__init__.py
tor/dialogue/balcony/__init__.py
tor/dialogue/balcony/view.rst
tor/dialogue/broomer/__init__.py
tor/dialogue/broomer/brooms.rst
tor/dialogue/butcher/__init__.py
tor/dialogue/butcher/meat.rst
tor/dialogue/chamber/__init__.py
tor/dialogue/chamber/rap.rst
tor/dialogue/chemist/__init__.py
tor/dialogue/chemist/pills.rst
tor/dialogue/inbound/__init__.py
tor/dialogue/inbound/jump.rst
tor/dialogue/outward/__init__.py
tor/dialogue/outward/death.rst
tor/dialogue/outward/fall.rst
tor/dialogue/stylist/__init__.py
tor/dialogue/stylist/wigs.rst
tor/static/audio/bass_to_fade.mp3
tor/static/audio/fly_away.mp3
tor/static/css/bfost.css
tor/static/fonts/aaparo-regular-webfont.woff
tor/static/fonts/aaparo-regular-webfont.woff2
tor/static/img/brushed-alum.png
tor/static/img/my-little-plaid.png
tor/static/img/street.jpg
tor/static/img/tower.jpg
tor/static/img/tower_of_rapunzel_inbound-shot.png
tor/test/__init__.py
tor/test/test_rules.py
tower_of_rapunzel-0.10.0.dist-info/COPYING
tower_of_rapunzel-0.10.0.dist-info/METADATA
tower_of_rapunzel-0.10.0.dist-info/WHEEL
tower_of_rapunzel-0.10.0.dist-info/entry_points.txt
tower_of_rapunzel-0.10.0.dist-info/top_level.txt
tower_of_rapunzel-0.10.0.dist-info/zip-safe
tower_of_rapunzel-0.10.0.dist-info/RECORD
