Metadata-Version: 2.1
Name: tower-of-rapunzel
Version: 0.10.0
Summary: A text-driven web game.
Home-page: https://github.com/tundish/tower_of_rapunzel
Author: D Haynes
Author-email: tundish@gigeconomy.org.uk
License: UNKNOWN
Platform: UNKNOWN
Classifier: Operating System :: OS Independent
Classifier: Programming Language :: Python :: 3.7
Classifier: Programming Language :: Python :: 3.8
Classifier: License :: OSI Approved :: GNU Affero General Public License v3 or later (AGPLv3+)
License-File: COPYING
Requires-Dist: aiohttp (>=3.6.1)
Requires-Dist: balladeer (>=0.14.0)
Provides-Extra: dev
Requires-Dist: flake8 (>=3.7.0) ; extra == 'dev'
Requires-Dist: wheel (>=0.33.0) ; extra == 'dev'
